odoo/addons/account_budget_oca/README.rst
odoo/addons/account_budget_oca/__init__.py
odoo/addons/account_budget_oca/__manifest__.py
odoo/addons/account_budget_oca/data/account_budget_demo.xml
odoo/addons/account_budget_oca/i18n/account_budget.pot
odoo/addons/account_budget_oca/i18n/account_budget_oca.pot
odoo/addons/account_budget_oca/i18n/af.po
odoo/addons/account_budget_oca/i18n/am.po
odoo/addons/account_budget_oca/i18n/ar.po
odoo/addons/account_budget_oca/i18n/bg.po
odoo/addons/account_budget_oca/i18n/bs.po
odoo/addons/account_budget_oca/i18n/ca.po
odoo/addons/account_budget_oca/i18n/cs.po
odoo/addons/account_budget_oca/i18n/da.po
odoo/addons/account_budget_oca/i18n/de.po
odoo/addons/account_budget_oca/i18n/el.po
odoo/addons/account_budget_oca/i18n/en_AU.po
odoo/addons/account_budget_oca/i18n/en_GB.po
odoo/addons/account_budget_oca/i18n/es.po
odoo/addons/account_budget_oca/i18n/es_BO.po
odoo/addons/account_budget_oca/i18n/es_CL.po
odoo/addons/account_budget_oca/i18n/es_CO.po
odoo/addons/account_budget_oca/i18n/es_CR.po
odoo/addons/account_budget_oca/i18n/es_EC.po
odoo/addons/account_budget_oca/i18n/es_PE.po
odoo/addons/account_budget_oca/i18n/es_PY.po
odoo/addons/account_budget_oca/i18n/es_VE.po
odoo/addons/account_budget_oca/i18n/et.po
odoo/addons/account_budget_oca/i18n/eu.po
odoo/addons/account_budget_oca/i18n/fa.po
odoo/addons/account_budget_oca/i18n/fi.po
odoo/addons/account_budget_oca/i18n/fo.po
odoo/addons/account_budget_oca/i18n/fr.po
odoo/addons/account_budget_oca/i18n/fr_BE.po
odoo/addons/account_budget_oca/i18n/fr_CA.po
odoo/addons/account_budget_oca/i18n/fr_FR.po
odoo/addons/account_budget_oca/i18n/gl.po
odoo/addons/account_budget_oca/i18n/gu.po
odoo/addons/account_budget_oca/i18n/he.po
odoo/addons/account_budget_oca/i18n/hi.po
odoo/addons/account_budget_oca/i18n/hr.po
odoo/addons/account_budget_oca/i18n/hu.po
odoo/addons/account_budget_oca/i18n/id.po
odoo/addons/account_budget_oca/i18n/is.po
odoo/addons/account_budget_oca/i18n/it.po
odoo14_addon_account_budget_oca-14.0.1.0.1.dist-info/METADATA
odoo14_addon_account_budget_oca-14.0.1.0.1.dist-info/WHEEL
odoo14_addon_account_budget_oca-14.0.1.0.1.dist-info/top_level.txt
odoo14_addon_account_budget_oca-14.0.1.0.1.dist-info/RECORD
